{
  "meta": {
    "app": "c1_hsch",
    "section": 1,
    "section_name": "LV1",
    "model": 18,
    "model_name": "Wochenendschlaf – mehr Schaden als Nutzen?",
    "level": "C1",
    "total_blanks": 6
  },
  "text": {
    "de": [
      {
        "type": "paragraph",
        "segments": [
          {
            "type": "text",
            "content": "„Dann schlafe ich eben am Wochenende länger!“ Diesen Satz hat wahrscheinlich jeder Berufstätige schon einmal gesagt oder zumindest gedacht. Denn wer morgens früh zur Arbeit gehen muss, bekommt an Werktagen selten genug Schlaf. Doch Schlafmangel erhöht auf Dauer das Risiko für Erkrankungen. "
          },
          {
            "type": "blank",
            "id": 1
          },
          {
            "type": "text",
            "content": " Unter anderem sorgen Wachstumshormone für die Reparatur von Zellschäden. Das Immunsystem nutzt diese Ruhepause, um den Kampf gegen Erreger zu intensivieren. "
          },
          {
            "type": "blank",
            "id": 2
          },
          {
            "type": "text",
            "content": " Zwar sind manche sogar stolz darauf, mit weniger als dieser empfohlenen Schlafmenge auszukommen, und denken, dass sie so ihre Leistungsfähigkeit unter Beweis stellen. Doch es steht außer Frage, dass Schlafmangel schädlich ist. Studien belegen, dass dieser nicht nur die Konzentration und geistige Leistungsfähigkeit beeinträchtigt, sondern auch den Stoffwechsel und das Herz-Kreislauf-System. Zu wenig Schlaf vermindert außerdem den Lernerfolg. Wer vor einer Prüfung bis in den Morgen paukt, müht sich womöglich vergebens: "
          },
          {
            "type": "blank",
            "id": 3
          },
          {
            "type": "text",
            "content": " Den meisten Menschen gelingt es im Alltag allerdings kaum, ausreichend zu schlafen. Schon am frühen Morgen klingelt der Wecker, und wenn man nach der Arbeit wenigstens noch ein wenig Zeit mit Familie, Hobbys oder Freunden verbringen möchte, führt dies fast zwangsläufig zu einem Schlafdefizit. Meist schafft man es erst am Wochenende, den fehlenden Schlaf durch langes Ausschlafen nachzuholen. "
          },
          {
            "type": "blank",
            "id": 4
          },
          {
            "type": "text",
            "content": " Das haben Professor Christopher Depner von der University of Colorado und seine Kollegen untersucht. Für ihre Studie teilten er und sein Team 36 gesunde junge Frauen und Männer in drei verschiedene Gruppen ein. "
          },
          {
            "type": "blank",
            "id": 5
          },
          {
            "type": "text",
            "content": " Die dritte Gruppe folgte dem typischen Wochenrhythmus von Berufstätigen: Montag bis Freitag nur fünf Stunden Schlaf, dann zwei Tage lang beliebig langes Ausschlafen. Bei allen Versuchspersonen kontrollierten die Forscher nach zwei Wochen unter anderem das Körpergewicht, die Kalorienzufuhr und die Essensmenge, aber auch den Spiegel des Schlafhormons Melatonin. Die Ergebnisse fielen ernüchternd aus: "
          },
          {
            "type": "blank",
            "id": 6
          },
          {
            "type": "text",
            "content": " Und das ist noch nicht alles: Wenig Schlaf führe zum Beispiel sogar dazu, dass man nach dem Abendessen mehr Süßigkeiten und Snacks esse, erklärt Professor Depner. „Das belegt, dass das Ausschlafen am Wochenende offenbar keine effektive Gegenmaßnahme gegen die Auswirkungen des chronischen Schlafmangel ist“, stellt er fest. Das bedeutet: Wer seinem Körper etwas Gutes tun möchte, sollte versuchen, täglich mindestens sieben Stunden Schlaf zu bekommen."
          }
        ]
      }
    ],
    "ar": [
      {
        "type": "paragraph",
        "segments": [
          {
            "type": "text",
            "content": "'إذن سأنام لفترة أطول في عطلة نهاية الأسبوع!' من المحتمل أن كل شخص عامل قد قال هذه الجملة أو على الأقل فكر فيها من قبل. لأن من يتعين عليه الذهاب إلى العمل في الصباح الباكر، نادراً ما يحصل على قسط كافٍ من النوم خلال أيام العمل العادية. ومع ذلك، فإن نقص النوم يزيد على المدى الطويل من خطر الإصابة بالأمراض. "
          },
          {
            "type": "blank",
            "id": 1
          },
          {
            "type": "text",
            "content": " ومن بين أمور أخرى، تضمن هرمونات النمو إصلاح التلف الخلوي، كما يستغل جهاز المناعة فترة الراحة هذه لتكثيف محاربته لمسببات الأمراض. "
          },
          {
            "type": "blank",
            "id": 2
          },
          {
            "type": "text",
            "content": " وصحيح أن البعض يفخرون بقدرتهم على العيش بأقل من كمية النوم الموصى بها، ويعتقدون أنهم بذلك يثبتون قدرتهم العالية على الأداء، إلا أنه لا ريب في أن نقص النوم أمر ضار ومؤذٍ؛ إذ تثبت الدراسات أن نقص النوم لا يضعف التركيز والقدرة العقلية فحسب، بل يؤثر سلباً أيضاً على عملية التمثيل الغذائي (الأيض) ونظام القلب والأوعية الدموية. كما أن قلة النوم تقلل من فرص النجاح في التعلم؛ فمن يدرس بجد حتى الصباح الباكر قبل الامتحان، قد يذهب جهده سدى: "
          },
          {
            "type": "blank",
            "id": 3
          },
          {
            "type": "text",
            "content": " ومع ذلك، لا يكاد معظم الناس ينجحون في النوم بشكل كافٍ في حياتهم اليومية؛ إذ يرن المنبه في الصباح الباكر، وعندما يرغب المرء في قضاء بعض الوقت بعد العمل مع العائلة أو الهوايات أو الأصدقاء، فإن هذا يؤدي حتماً إلى عجز في النوم. وغالباً لا يتمكن المرء من تعويض النوم المفقود عن طريق الاستغراق في النوم لفترة طويلة إلا في عطلة نهاية الأسبوع. "
          },
          {
            "type": "blank",
            "id": 4
          },
          {
            "type": "text",
            "content": " هذا ما بحثه البروفيسور كريستوفر ديبنر من جامعة كولورادو وزملائه. ومن أجل دراستهم، قام هو وفريقه بتقسيم 36 شاباً وشابة من الأصحاء إلى ثلاث مجموعات مختلفة. "
          },
          {
            "type": "blank",
            "id": 5
          },
          {
            "type": "text",
            "content": " واتبعت المجموعة الثالثة الإيقاع الأسبوعي النموذجي للموظفين: من الاثنين إلى الجمعة خمس ساعات فقط من النوم يومياً، ثم يومين من النوم الطويل كما يحلو لهم. وبعد أسبوعين، فحص الباحثون لدى جميع المتطوعين وزن الجسم، وكمية السعرات الحرارية، وكمية الطعام المستهلكة، وكذلك مستوى هرمون النوم (الميلاتونين). وجاءت النتائج مخيبة للآمال وصادمة: "
          },
          {
            "type": "blank",
            "id": 6
          },
          {
            "type": "text",
            "content": " ويوضح البروفيسور ديبنر أن هذا ليس كل شيء، بل إن قلة النوم تؤدي على سبيل المثال إلى تناول المزيد من الحلويات والوجبات الخفيفة بعد العشاء. ويؤكد قائلاً: 'هذا يثبت أن النوم الطويل في عطلة نهاية الأسبوع لا يبدو إشعاراً أو إجراءً مضاداً فعالاً للتخفيف من آثار النقص المزمن في النوم'. وهذا يعني: من أراد أن يقدم لجسده معروفاً، فعليه محاولة الحصول على سبع ساعات من النوم يومياً كحد أدنى."
          }
        ]
      }
    ]
  },
  "answers": [
    {
      "id": 1,
      "correct_key": "f",
      "options": [
        {
          "key": "a",
          "de": "So zeigte die Studie, dass unregelmäßige Schlafzeiten für den Körper zusätzlichen Stress bedeuten und die innere Uhr aus dem Takt bringen.",
          "ar": "حيث أظهرت الدراسة أن أوقات النوم غير المنتظمة تعني إجهاداً وضغطاً إضافياً على الجسم وتؤدي إلى إرباك الساعة البيولوجية الداخلية.",
          "keywords": {
            "de": "unregelmäßige Schlafzeiten, zusätzlichen Stress, innere Uhr",
            "ar": "أوقات نوم غير منتظمة، إجهاد إضافي، الساعة البيولوجية"
          }
        },
        {
          "key": "b",
          "de": "Die erste durfte neun Stunden pro Nacht schlafen, die zweite nur maximal fünf Stunden.",
          "ar": "سُمح للمجموعة الأولى بالنوم لمدة تسع ساعات في الليلة، بينما نامت المجموعة الثانية لمدة خمس ساعات كحد أقصى فقط.",
          "keywords": {
            "de": "erste durfte neun Stunden, zweite maximal fünf",
            "ar": "الأولى تسع ساعات، الثانية خمس ساعات كحد أقصى"
          }
        },
        {
          "key": "c",
          "de": "Aber kann man auf diese Weise die schädlichen Effekte des werktäglichen Schlafmangel tatsächlich ausgleichen?",
          "ar": "ولكن، هل يمكن للمرء بهذه الطريقة حقاً تعويض الآثار والأضرار الناجمة عن نقص النوم خلال أيام العمل؟",
          "keywords": {
            "de": "schädlichen Effekte ausgleichen, Schlafmangel",
            "ar": "تعويض الآثار الضارة، نقص النوم"
          }
        },
        {
          "key": "d",
          "de": "Denn das Gehirn braucht Schlaf, um Gelerntes abzuspeichern und zu verfestigen.",
          "ar": "ذلك لأن الدماغ بحاجة ماسة إلى النوم ليتمكن من حفظ المعلومات وتثبيت وتثمين ما تم تعلمه.",
          "keywords": {
            "de": "Gehirn braucht Schlaf, Gelerntes abzuspeichern",
            "ar": "الدماغ يحتاج النوم، حفظ ما تم تعلمه"
          }
        },
        {
          "key": "e",
          "de": "Es gibt also einige Gründe, warum Wissenschaftler zu mindestens sieben Stunden Schlaf pro Nacht raten.",
          "ar": "لذا، تتوفر جملة من الأسباب التي تجعل العلماء والباحثين ينصحون بالنوم لمدة سبع ساعات على الأقل في الليلة الواحدة.",
          "keywords": {
            "de": "einige Gründe, Wissenschaftler raten, sieben Stunden",
            "ar": "جملة من الأسباب، العلماء ينصحون، سبع ساعات"
          }
        },
        {
          "key": "f",
          "de": "Während man schläft, laufen nämlich viele Prozesse ab, die für die Regeneration von Körper und Geist entscheidend sind.",
          "ar": "فبينما يغط المرء في النوم، تجري في الواقع العديد من العمليات الحيوية الحاسمة والضرورية لتجديد ونقاهة الجسم والعقل.",
          "keywords": {
            "de": "während man schläft, Prozesse, Regeneration",
            "ar": "بينما ينام، عمليات حيوية، تجديد ونقاهة"
          }
        },
        {
          "key": "g",
          "de": "Außerdem ist es erwiesen, dass viele Menschen im Winter einen erhbelich höheren Schlafbedarf haben als im Sommer.",
          "ar": "بالإضافة إلى ذلك، فقد ثبت علمياً أن الكثير من الناس لديهم حاجة أكبر بكثير للنوم في فصل الشتاء مقارنة بفصل الصيف.",
          "keywords": {
            "de": "Winter, höheren Schlafbedarf, Sommer",
            "ar": "الشتاء، حاجة أكبر للنوم، الصيف"
          }
        },
        {
          "key": "h",
          "de": "Experten empfehlen dagegen, die letzte größere Mahlzeit etwa drei Stunden vor dem Schlafengehen einzunehmen.",
          "ar": "وفي المقابل، يوصي الخبراء بضرورة تناول الوجبة الرئيسية الأخيرة قبل حوالي ثلاث ساعات من التوجه إلى الفراش.",
          "keywords": {
            "de": "letzte größere Mahlzeit, drei Stunden vor dem Schlafengehen",
            "ar": "الوجبة الرئيسية الأخيرة، ثلاث ساعات قبل النوم"
          }
        }
      ]
    },
    {
      "id": 2,
      "correct_key": "e"
    },
    {
      "id": 3,
      "correct_key": "d"
    },
    {
      "id": 4,
      "correct_key": "c"
    },
    {
      "id": 5,
      "correct_key": "b"
    },
    {
      "id": 6,
      "correct_key": "a"
    }
  ]
}